paylike/__init__.py
paylike-1.0.dist-info/LICENSE
paylike-1.0.dist-info/METADATA
paylike-1.0.dist-info/WHEEL
paylike-1.0.dist-info/top_level.txt
paylike-1.0.dist-info/RECORD
